ytp_convert/__init__.py
ytp_convert/cli.py
ytp_convert/downloader.py
ytp_convert-1.1.0.dist-info/licenses/LICENSE
ytp_convert-1.1.0.dist-info/METADATA
ytp_convert-1.1.0.dist-info/WHEEL
ytp_convert-1.1.0.dist-info/entry_points.txt
ytp_convert-1.1.0.dist-info/top_level.txt
ytp_convert-1.1.0.dist-info/RECORD
