Metadata-Version: 2.4
Name: ytp-convert
Version: 1.1.0
Summary: A CLI tool to convert YouTube playlists into a single file
Author-email: Aaron Zachariah <aaron.zachariah@gmail.com>
License: MIT
Project-URL: Homepage, https://github.com/zachaa2/ytp-convert
Requires-Python: >=3.7
License-File: LICENSE
Requires-Dist: yt-dlp
Requires-Dist: pydub
Dynamic: license-file
